csviewer_tui/__init__.py
csviewer_tui/__main__.py
csviewer_tui/app.py
csviewer_tui/app.tcss
csviewer_tui/py.typed
csviewer_tui/version.py
csviewer_tui-0.2.1.dist-info/METADATA
csviewer_tui-0.2.1.dist-info/WHEEL
csviewer_tui-0.2.1.dist-info/entry_points.txt
csviewer_tui-0.2.1.dist-info/licenses/LICENSE
csviewer_tui-0.2.1.dist-info/RECORD
