Metadata-Version: 2.4
Name: csviewer-tui
Version: 0.2.1
Summary: CSViewer-TUI (cvit)
Project-URL: Homepage, https://github.com/sou-san/csviewer-tui
Project-URL: Repository, https://github.com/sou-san/csviewer-tui
Project-URL: Issues, https://github.com/sou-san/csviewer-tui/issues
Project-URL: Documentation, https://github.com/sou-san/csviewer-tui/blob/main/README.md
Author-email: sou-san <sou887867@gmail.com>
License: MIT License
License-File: LICENSE
Keywords: cli,csv,csviewer-tui,cvit,parquet,terminal,tool,tui,viewer
Classifier: Development Status :: 3 - Alpha
Classifier: Environment :: Console
Classifier: Intended Audience :: End Users/Desktop
Classifier: License :: OSI Approved :: MIT License
Classifier: Natural Language :: English
Classifier: Operating System :: Microsoft :: Windows :: Windows 10
Classifier: Operating System :: Microsoft :: Windows :: Windows 11
Classifier: Operating System :: POSIX :: Linux
Classifier: Programming Language :: Python :: 3
Classifier: Programming Language :: Python :: 3.10
Classifier: Programming Language :: Python :: 3.11
Classifier: Programming Language :: Python :: 3.12
Classifier: Programming Language :: Python :: 3.13
Classifier: Typing :: Typed
Requires-Python: >=3.10
Requires-Dist: click<9.0.0,>=8.1.7
Requires-Dist: textual-fastdatatable==0.12.0
Requires-Dist: textual<3.0.0,>=2.1.2
